siun/__init__.py
siun/__main__.py
siun/config.py
siun/criteria.py
siun/errors.py
siun/formatting.py
siun/main.py
siun/notification.py
siun/state.py
siun/util.py
siun-1.5.1.dist-info/METADATA
siun-1.5.1.dist-info/WHEEL
siun-1.5.1.dist-info/entry_points.txt
siun-1.5.1.dist-info/licenses/LICENSE.txt
siun-1.5.1.dist-info/RECORD
