Metadata-Version: 2.4
Name: siun
Version: 1.5.1
Summary: Report urgency of package upgrades
Project-URL: Documentation, https://github.com/t4k1t/siun#readme
Project-URL: Issues, https://github.com/t4k1t/siun/issues
Project-URL: Source, https://github.com/t4k1t/siun
Author-email: Thomas Kager <t4k1t+dev@protonmail.com>
License-Expression: MIT
License-File: LICENSE.txt
Classifier: Development Status :: 5 - Production/Stable
Classifier: License :: OSI Approved :: MIT License
Classifier: Programming Language :: Python
Classifier: Programming Language :: Python :: 3
Classifier: Programming Language :: Python :: 3.11
Classifier: Programming Language :: Python :: 3.12
Classifier: Programming Language :: Python :: 3.13
Classifier: Programming Language :: Python :: Implementation :: CPython
Requires-Python: >=3.11
Requires-Dist: click>=8.1
Requires-Dist: pydantic>=2.7
Provides-Extra: notification
Requires-Dist: dbus-python>=1.4.0; extra == 'notification'
